rag_pipeline/__init__.py
rag_pipeline/pipeline.py
rag_pipeline/utils.py
rag_pipeline/vector_stores.py
rag_pipeline-0.1.3.dist-info/LICENSE
rag_pipeline-0.1.3.dist-info/METADATA
rag_pipeline-0.1.3.dist-info/WHEEL
rag_pipeline-0.1.3.dist-info/top_level.txt
rag_pipeline-0.1.3.dist-info/RECORD
